{
    "Morgan Wallen": [],
    "Sabrina Carpenter": [],
    "Kendrick Lamar": [],
    "Drake": [],
    "Benson Boone": [],
    "Taylor Swift": [],
    "Zach Bryan": [],
    "Alex Warren": [],
    "SZA": [],
    "Luke Combs": [],
    "The Weeknd": [],
    "HUNTR/X: EJAE, Audrey Nuna & REI AMI": [],
    "Billie Eilish": [],
    "Shaboozey": [],
    "Fleetwood Mac": [],
    "Kesha": [],
    "KATSEYE": [],
    "Chappell Roan": [],
    "Jelly Roll": [],
    "Tate McRae": [],
    "Teddy Swims": [],
    "Toby Keith": [],
    "Lady Gaga": [],
    "Metallica": [],
    "Chris Stapleton": [],
    "Tyler, The Creator": [],
    "Post Malone": [],
    "Bruno Mars": [],
    "Ed Sheeran": [],
    "Bad Bunny": [
        "Hear This Music",
        "Rimas"
    ],
    "Saja Boys: Andrew Choi, Neckwav, Danny Chung, Kevin Woo & samUIL Lee": [],
    "sombr": [],
    "Radiohead": [],
    "Lorde": [
        "UMG",
        "Lava",
        "Republic"
    ],
    "Hozier": [],
    "Nirvana": [],
    "BigXthaPlug": [],
    "Jessie Murph": [],
    "ENHYPEN": [
        "Belift Lab",
        "Virgin/Universal Music Japan",
        "Universal Music Japan"
    ],
    "Bailey Zimmerman": [
        "Warner Bros",
        "Elektra"
    ],
    "Ella Langley": [],
    "Doechii": [],
    "Myles Smith": [],
    "Michael Jackson": [],
    "Miley Cyrus": [],
    "Playboi Carti": [],
    "Charli xcx": [
        "Vroom Vroom",
        "Warner Bros",
        "Asylum",
        "Atlantic",
        "Iamsound"
    ],
    "Fuerza Regida": [],
    "Lynyrd Skynyrd": [],
    "Ravyn Lenae": [],
    "Ariana Grande": [],
    "Chris Brown": [
        "CBE",
        "Jive",
        "RCA"
    ],
    "Gracie Abrams": [],
    "Riley Green": [],
    "Linkin Park": [],
    "Megan Moroney": [],
    "Leon Thomas": [],
    "Ozzy Osbourne": [],
    "AC/DC": [],
    "Creedence Clearwater Revival": [],
    "Zach Top": [],
    "Eagles": [],
    "Black Sabbath": [],
    "Karol G": [],
    "GloRilla": [],
    "Coldplay": [],
    "Vulfpeck": [],
    "Brandon Lake": [],
    "Tom Petty And The Heartbreakers": [],
    "Lainey Wilson": [],
    "Bruce Sprinsteen": [],
    "Led Zeppelin": [
        "Atlantic",
        "Swan Song"
    ],
    "Deftones": [],
    "The Beatles": [],
    "Oasis": [
        "Creation",
        "Epic",
        "Columbia",
        "Sony",
        "Big Brother",
        "Reprise"
    ],
    "Lana Del Rey": [],
    "My Chemical Romance": [],
    "Queen": [],
    "Tyler Childers": [],
    "The Marias": [],
    "The Beach Boys": [],
    "Stray Kids": [
        "JYP",
        "Epic Japan",
        "Republic"
    ],
    "Cardi B": [],
    "Thomas Rhett": [],
    "Forrest Frank": [],
    "Katy Perry": [],
    "Lola Young": [],
    "Mac Miller": [],
    "Pink Floyd": [],
    "Journey": [],
    "Noah Kahan": [],
    "ATEEZ": [],
    "Barbra Streisand": [],
    "Mariah The Scientist": [],
    "Sleep Token": [],
    "Red Hot Chili Peppers": [],
    "Luke Bryan": [],
    "Tucker Wetmore": [],
    "Lil Wayne": [
        "Universal",
        "Young Money",
        "Republic",
        "Cash Money"
    ],
    "Jason Aldean": []
}